{"v":"4.8.0","meta":{"g":"LottieFiles AE 1.0.0","a":"","k":"","d":"","tc":""},"fr":24,"ip":1440,"op":1489,"w":1200,"h":1200,"nm":"2_rigg","ddd":0,"assets":[],"layers":[{"ddd":0,"ind":1,"ty":4,"nm":"Layer 2 Outlines","sr":1,"ks":{"o":{"a":0,"k":100,"ix":11},"r":{"a":0,"k":0,"ix":10},"p":{"a":0,"k":[1150.783,315.532,0],"ix":2},"a":{"a":0,"k":[21.736,21.937,0],"ix":1},"s":{"a":1,"k":[{"i":{"x":[0.667,0.667,0.667],"y":[1,1,1]},"o":{"x":[0.333,0.333,0.333],"y":[0,0,0]},"t":1440,"s":[100,100,100]},{"i":{"x":[0.667,0.667,0.667],"y":[1,1,1]},"o":{"x":[0.333,0.333,0.333],"y":[0,0,0]},"t":1464,"s":[214.959,214.959,100]},{"t":1488,"s":[100,100,100]}],"ix":6}},"ao":0,"shapes":[{"ty":"gr","it":[{"ind":0,"ty":"sh","ix":1,"ks":{"a":0,"k":{"i":[[-1.218,0.196],[0,0],[3.167,0.441],[0,0],[0.19,1.276],[0,0],[0.435,-3.238],[0,0],[1.218,-0.197],[0,0],[-3.167,-0.441],[0,0],[-0.191,-1.276],[0,0],[-0.435,3.238],[0,0]],"o":[[0,0],[3.22,-0.442],[0,0],[-1.218,-0.148],[0,0],[-0.435,-3.238],[0,0],[-0.138,1.226],[0,0],[-3.22,0.441],[0,0],[1.218,0.147],[0,0],[0.435,3.238],[0,0],[0.137,-1.226]],"v":[[6.689,4.366],[18.266,2.699],[18.266,-2.845],[6.742,-4.415],[4.359,-6.82],[2.749,-18.448],[-2.749,-18.448],[-4.358,-6.77],[-6.689,-4.366],[-18.266,-2.698],[-18.266,2.845],[-6.742,4.415],[-4.358,6.819],[-2.749,18.449],[2.749,18.449],[4.359,6.771]],"c":true},"ix":2},"nm":"Path 1","mn":"ADBE Vector Shape - Group","hd":false},{"ty":"fl","c":{"a":0,"k":[0.337254901961,0.478431402468,1,1],"ix":4},"o":{"a":0,"k":100,"ix":5},"r":1,"bm":0,"nm":"Fill 1","mn":"ADBE Vector Graphic - Fill","hd":false},{"ty":"tr","p":{"a":0,"k":[21.736,21.937],"ix":2},"a":{"a":0,"k":[0,0],"ix":1},"s":{"a":0,"k":[100,100],"ix":3},"r":{"a":0,"k":0,"ix":6},"o":{"a":0,"k":100,"ix":7},"sk":{"a":0,"k":0,"ix":4},"sa":{"a":0,"k":0,"ix":5},"nm":"Transform"}],"nm":"Group 1","np":2,"cix":2,"bm":0,"ix":1,"mn":"ADBE Vector Group","hd":false}],"ip":1440,"op":4320,"st":0,"bm":0},{"ddd":0,"ind":2,"ty":4,"nm":"Layer 3 Outlines","sr":1,"ks":{"o":{"a":0,"k":100,"ix":11},"r":{"a":0,"k":0,"ix":10},"p":{"a":0,"k":[75.027,574.559,0],"ix":2},"a":{"a":0,"k":[48.515,48.946,0],"ix":1},"s":{"a":1,"k":[{"i":{"x":[0.667,0.667,0.667],"y":[1,1,1]},"o":{"x":[0.333,0.333,0.333],"y":[0,0,0]},"t":1440,"s":[100,100,100]},{"i":{"x":[0.667,0.667,0.667],"y":[1,1,1]},"o":{"x":[0.333,0.333,0.333],"y":[0,0,0]},"t":1464,"s":[36.008,36.008,100]},{"t":1488,"s":[100,100,100]}],"ix":6}},"ao":0,"shapes":[{"ty":"gr","it":[{"ind":0,"ty":"sh","ix":1,"ks":{"a":0,"k":{"i":[[-2.773,0.392],[0,0],[7.2,0.981],[0,0],[0.389,2.846],[0,0],[0.973,-7.262],[0,0],[2.773,-0.393],[0,0],[-7.201,-0.982],[0,0],[-0.389,-2.845],[0,0],[-0.973,7.261],[0,0]],"o":[[0,0],[7.152,-1.03],[0,0],[-2.774,-0.392],[0,0],[-0.973,-7.262],[0,0],[-0.389,2.797],[0,0],[-7.152,1.03],[0,0],[2.773,0.393],[0,0],[0.973,7.261],[0,0],[0.389,-2.797]],"v":[[15.083,9.838],[41.113,6.109],[41.065,-6.353],[15.132,-9.886],[9.78,-15.283],[6.179,-41.434],[-6.179,-41.434],[-9.78,-15.185],[-15.083,-9.837],[-41.113,-6.108],[-41.064,6.354],[-15.131,9.887],[-9.78,15.283],[-6.179,41.435],[6.179,41.435],[9.78,15.186]],"c":true},"ix":2},"nm":"Path 1","mn":"ADBE Vector Shape - Group","hd":false},{"ty":"fl","c":{"a":0,"k":[1,0.776470648074,0.20000001496,1],"ix":4},"o":{"a":0,"k":100,"ix":5},"r":1,"bm":0,"nm":"Fill 1","mn":"ADBE Vector Graphic - Fill","hd":false},{"ty":"tr","p":{"a":0,"k":[48.515,48.946],"ix":2},"a":{"a":0,"k":[0,0],"ix":1},"s":{"a":0,"k":[100,100],"ix":3},"r":{"a":0,"k":0,"ix":6},"o":{"a":0,"k":100,"ix":7},"sk":{"a":0,"k":0,"ix":4},"sa":{"a":0,"k":0,"ix":5},"nm":"Transform"}],"nm":"Group 1","np":2,"cix":2,"bm":0,"ix":1,"mn":"ADBE Vector Group","hd":false}],"ip":1440,"op":4320,"st":0,"bm":0},{"ddd":0,"ind":3,"ty":4,"nm":"Layer 4 Outlines","sr":1,"ks":{"o":{"a":0,"k":100,"ix":11},"r":{"a":0,"k":0,"ix":10},"p":{"a":0,"k":[684.753,627.331,0],"ix":2},"a":{"a":0,"k":[375.948,376.688,0],"ix":1},"s":{"a":0,"k":[100,100,100],"ix":6}},"ao":0,"shapes":[{"ty":"gr","it":[{"ind":0,"ty":"sh","ix":1,"ks":{"a":0,"k":{"i":[[9.413,0],[0,0],[0,-9.414],[-9.413,0],[0,0],[0,9.413]],"o":[[0,0],[-9.413,0],[0,9.413],[0,0],[9.413,0],[0,-9.414]],"v":[[51.871,-17.044],[-51.871,-17.044],[-68.915,0],[-51.871,17.043],[51.871,17.043],[68.915,0]],"c":true},"ix":2},"nm":"Path 1","mn":"ADBE Vector Shape - Group","hd":false},{"ty":"fl","c":{"a":0,"k":[0.835294177485,0.854902020623,0.898039275525,1],"ix":4},"o":{"a":0,"k":100,"ix":5},"r":1,"bm":0,"nm":"Fill 1","mn":"ADBE Vector Graphic - Fill","hd":false},{"ty":"tr","p":{"a":0,"k":[375.946,682.73],"ix":2},"a":{"a":0,"k":[0,0],"ix":1},"s":{"a":0,"k":[100,100],"ix":3},"r":{"a":0,"k":0,"ix":6},"o":{"a":0,"k":100,"ix":7},"sk":{"a":0,"k":0,"ix":4},"sa":{"a":0,"k":0,"ix":5},"nm":"Transform"}],"nm":"Group 1","np":2,"cix":2,"bm":0,"ix":1,"mn":"ADBE Vector Group","hd":false},{"ty":"gr","it":[{"ind":0,"ty":"sh","ix":1,"ks":{"a":0,"k":{"i":[[9.413,0],[0,0],[0,-9.414],[-9.413,0],[0,0],[0,9.413]],"o":[[0,0],[-9.413,0],[0,9.413],[0,0],[9.413,0],[0,-9.414]],"v":[[117.822,-17.043],[-117.822,-17.043],[-134.866,0],[-117.822,17.044],[117.822,17.044],[134.866,0]],"c":true},"ix":2},"nm":"Path 1","mn":"ADBE Vector Shape - Group","hd":false},{"ty":"fl","c":{"a":0,"k":[0.835294177485,0.854902020623,0.898039275525,1],"ix":4},"o":{"a":0,"k":100,"ix":5},"r":1,"bm":0,"nm":"Fill 1","mn":"ADBE Vector Graphic - Fill","hd":false},{"ty":"tr","p":{"a":0,"k":[375.944,607.145],"ix":2},"a":{"a":0,"k":[0,0],"ix":1},"s":{"a":0,"k":[100,100],"ix":3},"r":{"a":0,"k":0,"ix":6},"o":{"a":0,"k":100,"ix":7},"sk":{"a":0,"k":0,"ix":4},"sa":{"a":0,"k":0,"ix":5},"nm":"Transform"}],"nm":"Group 2","np":2,"cix":2,"bm":0,"ix":2,"mn":"ADBE Vector Group","hd":false},{"ty":"gr","it":[{"ind":0,"ty":"sh","ix":1,"ks":{"a":0,"k":{"i":[[9.413,0],[0,0],[0,-9.412],[-9.413,0],[0,0],[0,9.413]],"o":[[0,0],[-9.413,0],[0,9.413],[0,0],[9.413,0],[0,-9.412]],"v":[[117.822,-17.043],[-117.822,-17.043],[-134.866,0.001],[-117.822,17.044],[117.822,17.044],[134.866,0.001]],"c":true},"ix":2},"nm":"Path 1","mn":"ADBE Vector Shape - Group","hd":false},{"ty":"fl","c":{"a":0,"k":[0.835294177485,0.854902020623,0.898039275525,1],"ix":4},"o":{"a":0,"k":100,"ix":5},"r":1,"bm":0,"nm":"Fill 1","mn":"ADBE Vector Graphic - Fill","hd":false},{"ty":"tr","p":{"a":0,"k":[375.944,532.302],"ix":2},"a":{"a":0,"k":[0,0],"ix":1},"s":{"a":0,"k":[100,100],"ix":3},"r":{"a":0,"k":0,"ix":6},"o":{"a":0,"k":100,"ix":7},"sk":{"a":0,"k":0,"ix":4},"sa":{"a":0,"k":0,"ix":5},"nm":"Transform"}],"nm":"Group 3","np":2,"cix":2,"bm":0,"ix":3,"mn":"ADBE Vector Group","hd":false},{"ty":"gr","it":[{"ind":0,"ty":"sh","ix":1,"ks":{"a":0,"k":{"i":[[0,0],[0,0],[0,0],[0,0]],"o":[[0,0],[0,0],[0,0],[0,0]],"v":[[59.472,-94.577],[-94.577,59.472],[-59.472,94.578],[94.577,-59.471]],"c":true},"ix":2},"nm":"Path 1","mn":"ADBE Vector Shape - Group","hd":false},{"ty":"fl","c":{"a":0,"k":[1,0.776470648074,0.20000001496,1],"ix":4},"o":{"a":0,"k":100,"ix":5},"r":1,"bm":0,"nm":"Fill 1","mn":"ADBE Vector Graphic - Fill","hd":false},{"ty":"tr","p":{"a":0,"k":[410.456,357.14],"ix":2},"a":{"a":0,"k":[0,0],"ix":1},"s":{"a":0,"k":[100,100],"ix":3},"r":{"a":0,"k":0,"ix":6},"o":{"a":0,"k":100,"ix":7},"sk":{"a":0,"k":0,"ix":4},"sa":{"a":0,"k":0,"ix":5},"nm":"Transform"}],"nm":"Group 4","np":2,"cix":2,"bm":0,"ix":4,"mn":"ADBE Vector Group","hd":false},{"ty":"gr","it":[{"ind":0,"ty":"sh","ix":1,"ks":{"a":0,"k":{"i":[[0,0],[0,0],[0,0],[0,0]],"o":[[0,0],[0,0],[0,0],[0,0]],"v":[[69.165,34.059],[-34.059,-69.165],[-69.165,-34.058],[34.059,69.165]],"c":true},"ix":2},"nm":"Path 1","mn":"ADBE Vector Shape - Group","hd":false},{"ty":"fl","c":{"a":0,"k":[1,0.776470648074,0.20000001496,1],"ix":4},"o":{"a":0,"k":100,"ix":5},"r":1,"bm":0,"nm":"Fill 1","mn":"ADBE Vector Graphic - Fill","hd":false},{"ty":"tr","p":{"a":0,"k":[316.1,383.042],"ix":2},"a":{"a":0,"k":[0,0],"ix":1},"s":{"a":0,"k":[100,100],"ix":3},"r":{"a":0,"k":0,"ix":6},"o":{"a":0,"k":100,"ix":7},"sk":{"a":0,"k":0,"ix":4},"sa":{"a":0,"k":0,"ix":5},"nm":"Transform"}],"nm":"Group 5","np":2,"cix":2,"bm":0,"ix":5,"mn":"ADBE Vector Group","hd":false},{"ty":"gr","it":[{"ind":0,"ty":"sh","ix":1,"ks":{"a":0,"k":{"i":[[0,0],[0,0],[103.002,0],[68.173,66.692],[0,0]],"o":[[0,0],[-67.433,67.433],[-102.26,0],[0,0],[0,0]],"v":[[263.803,-286.775],[263.803,178.586],[0,286.775],[-263.803,178.586],[-263.803,-286.775]],"c":true},"ix":2},"nm":"Path 1","mn":"ADBE Vector Shape - Group","hd":false},{"ty":"fl","c":{"a":0,"k":[1,1,1,1],"ix":4},"o":{"a":0,"k":100,"ix":5},"r":1,"bm":0,"nm":"Fill 1","mn":"ADBE Vector Graphic - Fill","hd":false},{"ty":"tr","p":{"a":0,"k":[375.943,466.351],"ix":2},"a":{"a":0,"k":[0,0],"ix":1},"s":{"a":0,"k":[100,100],"ix":3},"r":{"a":0,"k":0,"ix":6},"o":{"a":0,"k":100,"ix":7},"sk":{"a":0,"k":0,"ix":4},"sa":{"a":0,"k":0,"ix":5},"nm":"Transform"}],"nm":"Group 6","np":2,"cix":2,"bm":0,"ix":6,"mn":"ADBE Vector Group","hd":false},{"ty":"gr","it":[{"ind":0,"ty":"sh","ix":1,"ks":{"a":0,"k":{"i":[[0,-207.485],[68.915,-68.175],[103.002,0],[68.174,66.691],[0,105.225],[-207.485,0]],"o":[[0,105.225],[-67.433,67.432],[-102.26,0],[-68.915,-68.175],[0,-208.227],[207.487,0]],"v":[[375.697,0],[263.803,268.25],[-0.001,376.438],[-263.803,268.25],[-375.698,0],[-0.001,-376.438]],"c":true},"ix":2},"nm":"Path 1","mn":"ADBE Vector Shape - Group","hd":false},{"ty":"fl","c":{"a":0,"k":[0.396078461292,0.341176470588,1,1],"ix":4},"o":{"a":0,"k":100,"ix":5},"r":1,"bm":0,"nm":"Fill 1","mn":"ADBE Vector Graphic - Fill","hd":false},{"ty":"tr","p":{"a":0,"k":[375.948,376.688],"ix":2},"a":{"a":0,"k":[0,0],"ix":1},"s":{"a":0,"k":[100,100],"ix":3},"r":{"a":0,"k":0,"ix":6},"o":{"a":0,"k":100,"ix":7},"sk":{"a":0,"k":0,"ix":4},"sa":{"a":0,"k":0,"ix":5},"nm":"Transform"}],"nm":"Group 7","np":2,"cix":2,"bm":0,"ix":7,"mn":"ADBE Vector Group","hd":false}],"ip":1440,"op":4320,"st":0,"bm":0},{"ddd":0,"ind":4,"ty":4,"nm":"Layer 5 Outlines","sr":1,"ks":{"o":{"a":0,"k":100,"ix":11},"r":{"a":0,"k":0,"ix":10},"p":{"a":1,"k":[{"i":{"x":0.667,"y":1},"o":{"x":0.333,"y":0},"t":1440,"s":[194.193,741.449,0],"to":[0,10.833,0],"ti":[0,0,0]},{"i":{"x":0.667,"y":1},"o":{"x":0.333,"y":0},"t":1464,"s":[194.193,806.449,0],"to":[0,0,0],"ti":[0,10.833,0]},{"t":1488,"s":[194.193,741.449,0]}],"ix":2},"a":{"a":0,"k":[38.784,38.783,0],"ix":1},"s":{"a":0,"k":[100,100,100],"ix":6}},"ao":0,"shapes":[{"ty":"gr","it":[{"ind":0,"ty":"sh","ix":1,"ks":{"a":0,"k":{"i":[[-21.28,0],[0,21.281],[21.281,0],[0,-21.281]],"o":[[21.281,0],[0,-21.281],[-21.28,0],[0,21.281]],"v":[[-0.001,38.533],[38.534,0],[-0.001,-38.533],[-38.534,0]],"c":true},"ix":2},"nm":"Path 1","mn":"ADBE Vector Shape - Group","hd":false},{"ty":"fl","c":{"a":0,"k":[1,0.776470648074,0.20000001496,1],"ix":4},"o":{"a":0,"k":100,"ix":5},"r":1,"bm":0,"nm":"Fill 1","mn":"ADBE Vector Graphic - Fill","hd":false},{"ty":"tr","p":{"a":0,"k":[38.784,38.783],"ix":2},"a":{"a":0,"k":[0,0],"ix":1},"s":{"a":0,"k":[100,100],"ix":3},"r":{"a":0,"k":0,"ix":6},"o":{"a":0,"k":100,"ix":7},"sk":{"a":0,"k":0,"ix":4},"sa":{"a":0,"k":0,"ix":5},"nm":"Transform"}],"nm":"Group 1","np":2,"cix":2,"bm":0,"ix":1,"mn":"ADBE Vector Group","hd":false}],"ip":1440,"op":4320,"st":0,"bm":0},{"ddd":0,"ind":5,"ty":4,"nm":"Layer 6 Outlines","sr":1,"ks":{"o":{"a":0,"k":100,"ix":11},"r":{"a":0,"k":0,"ix":10},"p":{"a":1,"k":[{"i":{"x":0.667,"y":1},"o":{"x":0.333,"y":0},"t":1440,"s":[320.908,359.08,0],"to":[0,-9.333,0],"ti":[0,0,0]},{"i":{"x":0.667,"y":1},"o":{"x":0.333,"y":0},"t":1464,"s":[320.908,303.08,0],"to":[0,0,0],"ti":[0,-9.333,0]},{"t":1488,"s":[320.908,359.08,0]}],"ix":2},"a":{"a":0,"k":[20.999,20.998,0],"ix":1},"s":{"a":0,"k":[100,100,100],"ix":6}},"ao":0,"shapes":[{"ty":"gr","it":[{"ind":0,"ty":"sh","ix":1,"ks":{"a":0,"k":{"i":[[-11.458,0],[0,11.46],[11.459,0],[0,-11.458]],"o":[[11.459,0],[0,-11.458],[-11.458,0],[0,11.46]],"v":[[0,20.748],[20.749,0],[0,-20.748],[-20.749,0]],"c":true},"ix":2},"nm":"Path 1","mn":"ADBE Vector Shape - Group","hd":false},{"ty":"fl","c":{"a":0,"k":[0.396078461292,0.341176470588,1,1],"ix":4},"o":{"a":0,"k":100,"ix":5},"r":1,"bm":0,"nm":"Fill 1","mn":"ADBE Vector Graphic - Fill","hd":false},{"ty":"tr","p":{"a":0,"k":[20.999,20.999],"ix":2},"a":{"a":0,"k":[0,0],"ix":1},"s":{"a":0,"k":[100,100],"ix":3},"r":{"a":0,"k":0,"ix":6},"o":{"a":0,"k":100,"ix":7},"sk":{"a":0,"k":0,"ix":4},"sa":{"a":0,"k":0,"ix":5},"nm":"Transform"}],"nm":"Group 1","np":2,"cix":2,"bm":0,"ix":1,"mn":"ADBE Vector Group","hd":false}],"ip":1440,"op":4320,"st":0,"bm":0},{"ddd":0,"ind":6,"ty":4,"nm":"Layer 7 Outlines","sr":1,"ks":{"o":{"a":0,"k":100,"ix":11},"r":{"a":0,"k":0,"ix":10},"p":{"a":1,"k":[{"i":{"x":0.667,"y":1},"o":{"x":0.333,"y":0},"t":1440,"s":[1072.303,241.259,0],"to":[0,5.5,0],"ti":[0,0,0]},{"i":{"x":0.667,"y":1},"o":{"x":0.333,"y":0},"t":1464,"s":[1072.303,274.259,0],"to":[0,0,0],"ti":[0,5.5,0]},{"t":1488,"s":[1072.303,241.259,0]}],"ix":2},"a":{"a":0,"k":[20.999,20.999,0],"ix":1},"s":{"a":0,"k":[100,100,100],"ix":6}},"ao":0,"shapes":[{"ty":"gr","it":[{"ind":0,"ty":"sh","ix":1,"ks":{"a":0,"k":{"i":[[-11.459,0],[0,11.46],[11.458,0],[0,-11.459]],"o":[[11.458,0],[0,-11.459],[-11.459,0],[0,11.46]],"v":[[0.001,20.748],[20.748,0],[0.001,-20.748],[-20.748,0]],"c":true},"ix":2},"nm":"Path 1","mn":"ADBE Vector Shape - Group","hd":false},{"ty":"fl","c":{"a":0,"k":[0.396078461292,0.341176470588,1,1],"ix":4},"o":{"a":0,"k":100,"ix":5},"r":1,"bm":0,"nm":"Fill 1","mn":"ADBE Vector Graphic - Fill","hd":false},{"ty":"tr","p":{"a":0,"k":[20.998,20.999],"ix":2},"a":{"a":0,"k":[0,0],"ix":1},"s":{"a":0,"k":[100,100],"ix":3},"r":{"a":0,"k":0,"ix":6},"o":{"a":0,"k":100,"ix":7},"sk":{"a":0,"k":0,"ix":4},"sa":{"a":0,"k":0,"ix":5},"nm":"Transform"}],"nm":"Group 1","np":2,"cix":2,"bm":0,"ix":1,"mn":"ADBE Vector Group","hd":false}],"ip":1440,"op":4320,"st":0,"bm":0},{"ddd":0,"ind":7,"ty":4,"nm":"Layer 8 Outlines","sr":1,"ks":{"o":{"a":0,"k":100,"ix":11},"r":{"a":0,"k":0,"ix":10},"p":{"a":1,"k":[{"i":{"x":0.667,"y":1},"o":{"x":0.333,"y":0},"t":1440,"s":[1027.842,350.188,0],"to":[0,-4.333,0],"ti":[0,0,0]},{"i":{"x":0.667,"y":1},"o":{"x":0.333,"y":0},"t":1464,"s":[1027.842,324.188,0],"to":[0,0,0],"ti":[0,-4.333,0]},{"t":1488,"s":[1027.842,350.188,0]}],"ix":2},"a":{"a":0,"k":[30.632,30.632,0],"ix":1},"s":{"a":0,"k":[100,100,100],"ix":6}},"ao":0,"shapes":[{"ty":"gr","it":[{"ind":0,"ty":"sh","ix":1,"ks":{"a":0,"k":{"i":[[-16.78,0],[0,16.78],[16.779,0],[0,-16.78]],"o":[[16.779,0],[0,-16.78],[-16.78,0],[0,16.78]],"v":[[0,30.382],[30.382,0],[0,-30.382],[-30.382,0]],"c":true},"ix":2},"nm":"Path 1","mn":"ADBE Vector Shape - Group","hd":false},{"ty":"fl","c":{"a":0,"k":[1,0.776470648074,0.20000001496,1],"ix":4},"o":{"a":0,"k":100,"ix":5},"r":1,"bm":0,"nm":"Fill 1","mn":"ADBE Vector Graphic - Fill","hd":false},{"ty":"tr","p":{"a":0,"k":[30.632,30.632],"ix":2},"a":{"a":0,"k":[0,0],"ix":1},"s":{"a":0,"k":[100,100],"ix":3},"r":{"a":0,"k":0,"ix":6},"o":{"a":0,"k":100,"ix":7},"sk":{"a":0,"k":0,"ix":4},"sa":{"a":0,"k":0,"ix":5},"nm":"Transform"}],"nm":"Group 1","np":2,"cix":2,"bm":0,"ix":1,"mn":"ADBE Vector Group","hd":false}],"ip":1440,"op":4320,"st":0,"bm":0}],"markers":[]}